{
    "classification": [
        {
            "title": "裸の王様",
            "rate": 0.1731090545654297
        },
        {
            "title": "かぐや姫",
            "rate": 0.13980898261070251
        },
        {
            "title": "浦島太郎",
            "rate": 0.11241449415683746
        },
        {
            "title": "一寸法師",
            "rate": 0.09599275887012482
        },
        {
            "title": "姨捨山",
            "rate": 0.06061427667737007
        },
        {
            "title": "眠る森のお姫様",
            "rate": 0.058734163641929626
        },
        {
            "title": "金太郎",
            "rate": 0.049789443612098694
        },
        {
            "title": "シンデレラ",
            "rate": 0.038888655602931976
        },
        {
            "title": "３匹の子豚",
            "rate": 0.034389838576316833
        },
        {
            "title": "青髭",
            "rate": 0.033175673335790634
        },
        {
            "title": "牛若と弁慶",
            "rate": 0.03209856152534485
        },
        {
            "title": "ブレーメンの音楽隊",
            "rate": 0.030693691223859787
        },
        {
            "title": "タニシの出世",
            "rate": 0.030511032789945602
        },
        {
            "title": "ヘンゼルとグレーテル",
            "rate": 0.01929847151041031
        },
        {
            "title": "こぶとり爺さん",
            "rate": 0.01821156032383442
        },
        {
            "title": "山姥",
            "rate": 0.017572779208421707
        },
        {
            "title": "桃太郎",
            "rate": 0.016217760741710663
        },
        {
            "title": "オオカミと７匹の子ヤギ",
            "rate": 0.010395835153758526
        },
        {
            "title": "さるかに合戦",
            "rate": 0.007930890657007694
        },
        {
            "title": "カチカチ山のたぬき",
            "rate": 0.004726305603981018
        },
        {
            "title": "赤ずきんちゃん",
            "rate": 0.004161591175943613
        },
        {
            "title": "和尚さんと小僧",
            "rate": 0.0035555840004235506
        },
        {
            "title": "花咲か爺さん",
            "rate": 0.003270157612860203
        },
        {
            "title": "舌切り雀",
            "rate": 0.0027325418777763844
        },
        {
            "title": "瓜子姫",
            "rate": 0.0019557576160877943
        }
    ],
    "story": "むかしむかし、町といなかに、大きなやしきをかまえて、金の上ぐつを片足落しました。それは、大きな金の箱に入れた純金製のものではありません。今日川で拾って来ました。桃太郎は、その時犬と猿と水晶しはから、お寺をぬけ出して僧正ガ谷へ行きました。四一寸待ちかまえが、「ごめん下さい。」とどなりました。すると、このさわぎで目をさまさこれは金貨と銀貨をいっぱい入れた金庫のかぎだ。これはふだん使わない金銀の皿を入れた戸棚のかぎだ。これは金貨と銀貨をいっぱい入れた金庫のかぎだ。これは金貨と銀貨をいっぱい入れた金庫のかぎだ。これは金貨と銀貨をいっぱい入れた金庫のかぎだ。これはふだん使わない金銀の皿を入れた戸棚のかぎだ。これは金貨と銀貨をいっぱい入れた金庫のかぎだ。これはみんな青ひげが、ひとりひとり、結婚したあとで、奥がたにこたえました。「さあ、ここらではついとあいてございましたの。」と、お姫さまが、ひとり、門を出て行くところを見なかったか。」と、いいました。こんなことで、心配や苦労はきれいにふきとんでしまいました。そして、「さあ、そこらで、みんな行って、ごろた石をひろっておいで。」サンドリヨンは、いずれそのうちに青ひげが、大きな剣をぬいて手にもっていたかぎが、いつか、すべり落ちたのも知らずにいたくらいです。しばらくしておじいさんは、それで、おおかみのおなかのなかにいっぱい、つめました。やがて、待ちに待った、たのしい日になりました。三ばんめの妖女は、めいめい、ひとつずつ、りっぱなおくりものを持って来るはずでした。なにもかも、気味のわるい"
}